{
  "id": "gl_block-beta_00246",
  "source": "gitlab",
  "source_url": "https://github.com/Gurankio/mmd/blob/c572c7f2466f63a78212189e33b31c5dcc0d1b2f/input.mmd",
  "source_note": "collected_from_github_additional",
  "github_repo": "Gurankio/mmd",
  "diagram_type": "block-beta",
  "code": "Title testing!\nAnd there might be a subtitle.\n That is pretty long.\n---\n\nParagraph testing.\nStill the same paragraph but on a new line.\nA continued line on 3 source-lines,\n  this is the second source-line and\n  this is the third source-line.\n  This is a new sentence on the same \"line\".\n\nThis is a new paragraph.\n-> This thing with arrows renders correctly!\n-> On 2 separate lines.\n\n### A chapter-like\n    The chapter introduction.\n\n    # Example header\n      That has some content\n\n    This is in the chapter-like.\n\nThis is in the root!\n\n# Styles\n  Some **bold text** and a bold *word*!\n  Some __italic text__ and an italic _word_!\n  Some ~~strikethrough text~~ and a strikethrough ~word~!\n  Some ``monospaced text``    and a monospaced `word`!\n\n# Quotes and specifications\n  A big paragraph that has a [special] meaning.\n  > Special here means that it is really [extraordinary].\n    > Meaning something insane, even nested!\n      Nested comment.\n    First level continued comment,\n     that spans two lines.\n  Continuing the sentence with a _special_ meaning.\n\n  > This instead is just an aside comment.\n    Might be anything really.\n\n  > A quote or smth with a title!\n    ---\n\n    Pretty cool.\n\n# Lists\n  Now a series of lists, notice how they are part of the surrounding paragraph:\n  A.\n  B. This item has a very long source-description,\n     It even goes on multiple source-lines!\n  C.\n  I can continue the paragraph here (as there is no indent).\n\n  Dashed list:\n   - P1\n   - P2\n   - P3\n   - P4\n\n  Numbered list:\n  1.\n  2.\n     2.1.\n     2.2.\n  3.\n\n  Roman list:\n  I.   Arbitrary spaces after list marker.\n  II.\n       II.1. Nested mixed list!\n             That can of course span multiple lines.\n\n             AND multiple paragraphs!\n  III.\n\n# Monospace blocks\n  Adding the ability to add monospaced blocks:\n  ```\n  lorem ipsum,\n   continued lorem ipsum\n\n  A. lorem ipsum\n  B. lorem ipsum\n  ```\n  And you can continue afterwards.\n\n  Trying blocks some more\n  ```\n  A code block.\n  ```\n  > Followed by an aside...\n    That has a code block in it:\n    ```\n        Nested code block.\n\n\n    ```\n    Followed by another line.\n\n  Seems to be working.\n",
  "content_size": 2152,
  "collected_at": "2026-02-06T14:05:20.530672",
  "compilation_status": "failed",
  "compilation_error": "[WinError 2] 系统找不到指定的文件。",
  "license": "mit",
  "license_name": "MIT License",
  "license_url": "https://api.github.com/licenses/mit",
  "repo_stars": 0,
  "repo_forks": 0,
  "repo_owner": "Gurankio",
  "repo_name": "mmd",
  "repo_description": "A markdown flavor to preserve the look and feel of the source files",
  "repo_language": "Python",
  "repo_topics": [],
  "repo_created_at": "2025-04-25T19:40:46Z",
  "repo_updated_at": "2025-04-25T19:43:57Z"
}