{
  "id": "gl_sequence_00026",
  "source": "gitlab",
  "source_url": "https://gitlab.com/WarheadsSE/gitlab-diagrams",
  "gitlab_project": "WarheadsSE/gitlab-diagrams",
  "diagram_type": "sequence",
  "code": "sequenceDiagram\n    Client->>+LoadBalancer: HTTPS GET /\n    LoadBalancer->>+NGINX: HTTP(S) GET /\n    loop route\n        NGINX ->> NGINX: Route based on Host/ServerAlias\n    end\n    NGINX->>+Webservice: HTTP GET /\n    Webservice->>-NGINX: HTTP 302/200 (content)\n    NGINX->>-LoadBalancer: HTTP 302/200 (content)\n    LoadBalancer->>-Client: HTTP 302/200 (content)",
  "content_size": 362,
  "collected_at": "2026-02-06T10:57:07.625980",
  "compilation_status": "success",
  "license": "gitlab_repo",
  "license_name": "GitLab Repository (refer to project page)"
}