{
  "id": "gl_timeline_00085",
  "source": "gitlab",
  "source_url": "https://github.com/maeddes/spring-boot-and-container/blob/d47f87540bf2df1aa41631a8ff96a1b5dd8d091e/mermaid/springboot.mmd",
  "source_note": "collected_from_github_additional",
  "github_repo": "maeddes/spring-boot-and-container",
  "diagram_type": "timeline",
  "code": "timeline\n    title Spring, and Spring Boot Timeline\n\n    1995 : Java 1.0 released by Sun Microsystems\n    2002 : J2EE becomes dominant but complex\n    2003 : Spring Framework 1.0 released (Rod Johnson)\n    2014 : Spring Boot 1.0 - Auto-config, Embedded servers, Initializr\n    2015 : Spring Boot 1.3 - Actuator introduced\n    2016 : Spring Boot 1.4 - Improved testing support\n    2017 : Spring Cloud matures - Microservices support\n    2020 : Spring Boot 2.3 - Buildpacks, container support\n    2021 : Spring Native (GraalVM support)\n    2022 : Spring Boot 3.0 - Jakarta EE migration, GraalVM native images\n    2023 : Spring Boot 3.1 - Testcontainers integration\n    2023 : Spring Boot 3.1 - Docker Compose support\n\n",
  "content_size": 716,
  "collected_at": "2026-02-06T14:02:28.990132",
  "compilation_status": "success",
  "license": "none",
  "license_name": "No License",
  "license_url": "",
  "repo_stars": 31,
  "repo_forks": 7,
  "repo_owner": "maeddes",
  "repo_name": "spring-boot-and-container",
  "repo_description": "Code and stuff for the conference talk",
  "repo_language": "Java",
  "repo_topics": [],
  "repo_created_at": "2025-03-11T09:31:02Z",
  "repo_updated_at": "2026-02-06T07:34:03Z"
}