{
  "id": "aug_gl_packet-beta_00379_Inf_3",
  "source": "augmented_real_structure",
  "source_url": "https://github.com/creadri/sebastianjs/blob/68f26b77f247c9253ffa2707ccc9ce4d0a3067a1/samples/mermaid-demos/packet__2.mmd",
  "source_note": "collected_from_github_additional",
  "github_repo": "creadri/sebastianjs",
  "diagram_type": "packet-beta",
  "code": "---\nconfig:\n  packet:\n    showBits: false\n---\npacket\n  0-15: \"Source Port\"\n  16-31: \"Destination Port\"\n  32-63: \"Sequence Number\"\n  64-95: \"Acknowledgment Number\"\n  96-99: \"Data Offset\"\n  100-105: \"Reserved\"\n  106: \"URG\"\n  107: \"ACK\"\n  108: \"PSH\"\n  109: \"RST\"\n  110: \"SYN\"\n  111: \"FIN\"\n  112-127: \"Window\"\n  128-143: \"Checksum\"\n  144-159: \"Urgent Pointer\"\n  160-191: \"(Infra_LoadBalancer)\"\n  192-223: \"data\"",
  "content_size": 408,
  "collected_at": "2026-02-06T14:08:34.722896",
  "compilation_status": "failed",
  "license": "gitlab_repo",
  "license_name": "GitLab Repository",
  "license_url": "https://gitlab.com",
  "compilation_error": "[WinError 2] 系统找不到指定的文件。",
  "augmentation_domain": "Infra",
  "seed_id": "gl_packet-beta_00379"
}