{
  "id": "aug_gl_kanban_00472_Edu_4",
  "source": "augmented_real_structure",
  "source_url": "https://github.com/udlose/MermaidPad/blob/70269c8831e653a432d4ca2cc25b87c824974b3f/Examples/Kanban.mmd",
  "source_note": "collected_from_github_additional",
  "github_repo": "udlose/MermaidPad",
  "diagram_type": "kanban",
  "code": "---\nconfig:\n  kanban:\n    ticketBaseUrl: 'https://github.com/mermaid-js/mermaid/issues/#TICKET#'\n---\nkanban\n  Todo\n    [Education_ContentCDN]\n    docs[Education_GradeSync]\n  [Education_ContentCDN]\n    id6[Education_ContentCDN]\n  id9[Education_ClassroomService]\n    id8[Education_LMS_Portal]@{Education_StudentDB}\n  id10[Education_ClassroomService]\n    id4[Education_ClassroomService]@{Education_GradeSync}\n    id66[Education_ContentCDN]@{Education_LMS_Portal}\n  id11[Education_StudentDB]\n    id5[Education_StudentDB]\n    id2[Education_ContentCDN]@{Education_ContentCDN}\n    id3[Education_GradeSync]@{Education_ContentCDN}\n\n  id12[Education_ClassroomService]\n    id3[Education_ContentCDN]\n",
  "content_size": 908,
  "collected_at": "2026-02-06T14:10:33.248440",
  "compilation_status": "failed",
  "license": "gitlab_repo",
  "license_name": "GitLab Repository",
  "license_url": "https://gitlab.com",
  "compilation_error": "[WinError 2] 系统找不到指定的文件。",
  "augmentation_domain": "Education",
  "seed_id": "gl_kanban_00472"
}