{
  "id": "aug_gh_mindmap_02083_Ret_8",
  "source": "augmented_real_structure",
  "source_url": "https://github.com/danindiana/PathfinderLM/blob/059ebe5f8b4a57dba658160184d339a42199f739/ellipsis/ellipsis_mindmap.mmd",
  "github_repo": "danindiana/PathfinderLM",
  "github_file_path": "ellipsis/ellipsis_mindmap.mmd",
  "diagram_type": "mindmap",
  "code": "mindmap\n  root(Retail_Inventory))\n    sub(Retail_CouponSystem)\n      A1[Retail_CustomerLoyalty]\n      A2[Retail_CouponSystem]\n      B1[Retail_CouponSystem]\n      B2[Retail_Inventory]\n    sub(Retail_Inventory)\n      C1[Retail_OrderManagement]\n      C2[Retail_PointOfSale]\n      D1[Retail_Inventory]\n      D2[Retail_CustomerLoyalty]\n    sub(Retail_PointOfSale)\n      E1[Retail_Inventory]\n      E2[Retail_OrderManagement]\n      G1[Retail_OrderManagement]\n      G2[Retail_PointOfSale]\n    sub(Retail_PointOfSale)\n      F1[Retail_OrderManagement]\n      F2[Retail_CouponSystem]\n      H1[Retail_CouponSystem]\n      H2[Retail_CouponSystem]\n      J1[Retail_CouponSystem]\n      J2[Retail_OrderManagement]\n    sub(Retail_CouponSystem)\n      L1[Retail_Inventory]\n      L2[Retail_PointOfSale]\n      M1[Retail_PointOfSale]\n      M2[Retail_PointOfSale]\n      N1[Retail_CouponSystem]\n      N2[Retail_CouponSystem]\n\n    sub(Retail_CustomerLoyalty)\n      I1[Retail_CouponSystem]\n      I2[Retail_Inventory]\n      K1[Retail_CustomerLoyalty]\n      K2[Retail_Inventory]\n",
  "content_size": 1129,
  "collected_at": "2026-02-06T02:07:32.700987",
  "compilation_status": "success",
  "license": "gpl-3.0",
  "license_name": "GNU General Public License v3.0",
  "license_url": "https://api.github.com/licenses/gpl-3.0",
  "repo_stars": 0,
  "repo_forks": 0,
  "repo_owner": "danindiana",
  "repo_name": "PathfinderLM",
  "repo_description": "Personalized life coach system leveraging Language Models, Retrieval Augmented Generators (RAG).",
  "repo_language": "Shell",
  "repo_topics": [],
  "repo_created_at": "2024-07-05T03:07:33Z",
  "repo_updated_at": "2025-11-15T19:17:47Z",
  "augmentation_domain": "Retail",
  "seed_id": "gh_mindmap_02083"
}