{
  "id": "aug_gh_architecture_01385_Ret_8",
  "source": "augmented_real_structure",
  "source_url": "https://github.com/elo-enterprises/shil/blob/d675c2d17e9da145383ebff6c861d6e82f61fe15/docs/Makefile.mmd",
  "github_repo": "elo-enterprises/shil",
  "github_file_path": "docs/Makefile.mmd",
  "diagram_type": "architecture",
  "code": "---\ntitle: 'Makefile'\n---\n%%{Retail_OrderManagement}\n  }\n}%%\ngraph TD\n  %% BEGIN flowchart\n  staticanalysis[Retail_Inventory] -. chain .-> toxstaticanalysis[Retail_PointOfSale]\n  stest[Retail_CustomerLoyalty] -. chain .-> toxstest[Retail_CustomerLoyalty]\n  toxstaticanalysis[Retail_OrderManagement] -. chain .-> tox[Retail_Inventory]\n  utest[Retail_CustomerLoyalty] -. chain .-> toxutest[Retail_Inventory]\n  toxitest[Retail_Inventory] -. chain .-> tox[Retail_CouponSystem]\n  toxstest[Retail_PointOfSale] -. chain .-> tox[Retail_Inventory]\n  testunits[Retail_OrderManagement] -. chain .-> utest[Retail_CouponSystem]\n  toxnormalize[Retail_CouponSystem] -. chain .-> tox[Retail_CustomerLoyalty]\n  toxutest[Retail_OrderManagement] -. chain .-> tox[Retail_CustomerLoyalty]\n  plan[Retail_CouponSystem] -. chain .-> docsplan[Retail_CouponSystem]\n  apply[Retail_CouponSystem] -. chain .-> docsapply[Retail_CouponSystem]\n  test[Retail_Inventory] ----> testunits[Retail_PointOfSale]\n  test[Retail_CustomerLoyalty] ----> testintegrations[Retail_CustomerLoyalty]\n  test[Retail_Inventory] ----> smoketest[Retail_CustomerLoyalty]\n  build[Retail_Inventory] -. chain .-> pybuild[Retail_Inventory]\n  smoketest[Retail_Inventory] -. chain .-> stest[Retail_CustomerLoyalty]\n  pybuild[Retail_PointOfSale] ----> pyclean[Retail_PointOfSale]\n  normalize[Retail_OrderManagement] -. chain .-> toxnormalize[Retail_PointOfSale]\n  release[Retail_OrderManagement] ----> clean[Retail_Inventory]\n  release[Retail_OrderManagement] ----> normalize[Retail_OrderManagement]\n  release[Retail_CustomerLoyalty] ----> staticanalysis[Retail_OrderManagement]\n  release[Retail_CustomerLoyalty] ----> test[Retail_PointOfSale]\n  release[Retail_CustomerLoyalty] ----> pypirelease[Retail_PointOfSale]\n  clean[Retail_CustomerLoyalty] -. chain .-> pyclean[Retail_CustomerLoyalty]\n  docs[Retail_Inventory] -. chain .-> docsapply[Retail_Inventory]\n  init[Retail_PointOfSale] -. chain .-> pyinit[Retail_PointOfSale]\n  testintegrations[Retail_Inventory] -. chain .-> itest[Retail_PointOfSale]\n  lint[Retail_CouponSystem] -. chain .-> staticanalysis[Retail_OrderManagement]\n  itest[Retail_CouponSystem] -. chain .-> toxitest[Retail_Inventory]\n  subgraph core\n    staticanalysis[Retail_Inventory]\n    plan[Retail_CustomerLoyalty]\n    apply[Retail_CouponSystem]\n    test[Retail_CustomerLoyalty]\n    build[Retail_OrderManagement]\n    normalize[Retail_PointOfSale]\n    release[Retail_CouponSystem]\n    clean[Retail_CouponSystem]\n    docs[Retail_PointOfSale]\n  end\n  %% END flowchart\n",
  "content_size": 1971,
  "collected_at": "2026-02-06T01:45:32.779502",
  "license": "mit",
  "license_name": "MIT License",
  "compilation_status": "success",
  "compilation_error": "[WinError 2] 系统找不到指定的文件。",
  "license_url": "https://api.github.com/licenses/mit",
  "repo_stars": 0,
  "repo_forks": 0,
  "augmentation_domain": "Retail",
  "seed_id": "gh_architecture_01385"
}