{
  "id": "gh_ind_99ef9aaab0",
  "source": "github_industrial",
  "repo": "raamcosta/compose-destinations",
  "license": "apache-2.0",
  "code": "---\ntitle: MyTopLevel Navigation Graph\n---\n%%{init: {'theme':'base', 'themeVariables': { 'primaryTextColor': '#fff' }}%%\ngraph TD\nmy_top_level([\"MyTopLevelGraph\"]) -- \"start\" --- asd(\"Asd\")\n\n\nclassDef destination fill:#5383EC,stroke:#ffffff;\nclass asd destination;\nclassDef navgraph fill:#63BC76,stroke:#ffffff;\nclass my_top_level navgraph;\n",
  "diagram_type": "graph size:250..400",
  "collected_at": "2026-02-27T04:29:42.473882"
}