{
  "id": "gh_ind_b7d2fbef1b",
  "source": "github_industrial",
  "repo": "1jehuang/mermaid-rs-renderer",
  "license": "mit",
  "code": "flowchart LR\n  subgraph ClusterA\n    A1[Ingress]\n    A2[Transform]\n    A1 --> A2\n  end\n  subgraph ClusterB\n    B1[Normalize]\n    B2[Enrich]\n    B1 --> B2\n  end\n  subgraph ClusterC\n    C1[Persist]\n    C2[Notify]\n    C1 --> C2\n  end\n\n  A2 --> B1\n  B2 --> C1\n  C2 --> A1\n\n  A1 -.sync.-> B2\n  B1 -.sync.-> C2\n  C1 -.sync.-> A2\n",
  "diagram_type": "subgraph size:250..400",
  "collected_at": "2026-02-27T04:47:55.656931"
}