{
  "id": "ot_gantt_00610",
  "source": "other",
  "source_url": "https://github.com/creadri/sebastianjs/blob/68f26b77f247c9253ffa2707ccc9ce4d0a3067a1/samples/mermaid-demos/gantt__10.mmd",
  "source_type": "github_search_special",
  "github_repo": "creadri/sebastianjs",
  "diagram_type": "gantt",
  "code": "---\n  displayMode: compact\n---\ngantt\ntitle GANTT compact\ndateFormat  HH:mm:ss\naxisFormat  %Hh%M\n\nsection DB Clean\nClean: 12:00:00, 10m\nClean: 12:30:00, 12m\nClean: 13:00:00, 8m\nClean: 13:30:00, 9m\nClean: 14:00:00, 13m\nClean: 14:30:00, 10m\nClean: 15:00:00, 11m\n\nsection Sessions\nA: 12:00:00, 63m\nB: 12:30:00, 12m\nC: 13:05:00, 12m\nD: 13:06:00, 33m\nE: 13:15:00, 55m\nF: 13:20:00, 12m\nG: 13:32:00, 18m\nH: 13:50:00, 20m\nI: 14:10:00, 10m",
  "content_size": 429,
  "collected_at": "2026-02-06T10:44:42.423945",
  "compilation_status": "success",
  "license": "mit",
  "license_name": "MIT License",
  "license_url": "https://api.github.com/licenses/mit",
  "repo_stars": 7,
  "repo_forks": 0,
  "repo_owner": "creadri",
  "repo_name": "sebastianjs",
  "repo_description": "Mermaid wrapper in order to be able to perform server-side svg renderers without headless browsers DOM.",
  "repo_language": "JavaScript",
  "repo_topics": [],
  "repo_created_at": "2025-09-02T07:03:38Z",
  "repo_updated_at": "2026-01-23T22:22:43Z"
}