{
  "id": "gh_er_02345",
  "source": "github",
  "source_url": "https://github.com/LeonSlent/ONG/blob/e2a00b9822f31be8929ee36ceece6c4d3e217ba4/DER.mmd",
  "github_repo": "LeonSlent/ONG",
  "github_file_path": "DER.mmd",
  "diagram_type": "er",
  "code": "---\ntitle: ONG DER\n---\nerDiagram\nUser{\n    CPF Integer(11) PK \"NOT NULL\" \n    Nome String(100) \"NOT NULL\"\n    Email String(100) \"NOT NULL\"\n    Pass TEXT \"NOT NULL\"\n}\n\nTelUser{\n    CPF Integer(11) FK \"NOT NULL\"\n    Tel Integer(11) PK \"NOT NULL\"\n    Ident String(36) \"NULLABLE\"\n}\n\nAdmin{\n    Mat String(36) PK \"DEFAULT(uuid4()), NOT NULL\"\n    Nome String(100) \"NOT NULL\"\n    Email String(100) \"NOT NULL\"\n    CPF Integer(11) \"NOT NULL\"\n    Pass TEXT \"NOT NULL\"\n}\n\nTel{\n    Mat Integer(36) FK \"DEFAULT(uuid4()), NOT NULL\"\n    Tel Integer(11) PK \"NOT NULL\"\n    Ident String(36) \"NULLABLE\"\n}\n\nAnimal{\n    ID Integer(10) PK \"DEFAULT(AUTOINCREMENT), NOT NULL\"\n    Port String(30) \"NOT NULL\"\n    Race String(30) \"NOT NULL\"\n    Type String(30) \"NOT NULL\"\n    Cast Bool \"DEFAULT(False) ,NOT NULL\"\n    Pic BLOB \"DEFAULT(IMAGE_PLACE), NOT NULL\"\n}\n\nHistory{\n    ID String(36) PK \"DEFAULT(uuid4()), NOT NULL\"\n    Date DATETIME \"DEFAULT(Datetime.now()), NOT NULL\"\n    Status String(20) \"DEFAULT(Idle), NOT NULL\"\n    Animal Integer(10) FK \"From(Animal.ID), NOT NULL\"\n    Reciver Integer(11) FK \"From(User.CPF), NOT NULL\"\n    Aproval Integer(36) FK \"From(Admin.Mat), NOT NULL\"\n}\n\nUser ||--o{ TelUser : \"has\"\nAdmin ||--o{ Tel : \"has\"\nHistory ||--o{ Animal : \"has\"\nHistory ||--o{ User : \"has\"\nHistory ||--o{ Admin : \"has\"\n\n",
  "content_size": 1303,
  "collected_at": "2026-02-06T02:11:35.763007",
  "compilation_status": "failed",
  "license": "mit",
  "license_name": "MIT License",
  "license_url": "https://api.github.com/licenses/mit",
  "repo_stars": 1,
  "repo_forks": 0,
  "repo_owner": "LeonSlent",
  "repo_name": "ONG",
  "repo_description": "Projeto final em desenvolvimento por Leonardo Martins, Beatriz Ivano e Marcelo Ribeiro da disciplina de orientação a objetos do TERCEIRO SEMESTRE de analise e desenvolvimento de sistemas - IFPR",
  "repo_language": "HTML",
  "repo_topics": [],
  "repo_created_at": "2025-03-27T11:52:04Z",
  "repo_updated_at": "2025-09-19T19:13:01Z",
  "compilation_error": "[WinError 2] 系统找不到指定的文件。"
}