{
  "id": "gh_mindmap_02245",
  "source": "github",
  "source_url": "https://github.com/jhao/pm-universe/blob/a74de2855629453b6d326c1e419d846499a1591c/slides/diagrams/enterprise/sap-public-sector.mmd",
  "github_repo": "jhao/pm-universe",
  "github_file_path": "slides/diagrams/enterprise/sap-public-sector.mmd",
  "diagram_type": "mindmap",
  "code": "%% Auto-generated by scripts/generate_assets.py\nmindmap\n  root((SAP Public Sector 功能结构))\n    目标用户(财政部门、公共服务机构、政务运营团队)\n    核心痛点(预算执行透明度低、跨部门协同不足、合规要求严苛)\n    价值主张(提供从预算规划、征收到公共服务的一体化数字平台)\n    核心场景\n      财政部门制定预算并跟踪执行\n      税务征收与收入管理\n      公共服务项目监控绩效\n    功能模块\n      公共财务管理(提升预算与资金管理透明度)\n        预算编制、审批与执行监控\n        资金管理与现金预测\n        财务报表与合规报送\n      税费征收(提升征收效率与纳税人体验)\n        纳税人档案与申报管理\n        催缴与欠税管理\n        在线服务与自助门户\n      公共服务项目(跟踪公共项目绩效)\n        项目规划、合同与采购\n        绩效指标与成果评估\n        项目资金与合规管理\n      公民服务与互动(提升公众参与与服务质量)\n        多渠道服务请求与工单\n        公民门户与移动应用\n        反馈收集与满意度分析\n    关键指标\n      预算执行率与偏差\n      税收征管效率与欠税率\n      公共项目准时率与公众满意度\n",
  "content_size": 641,
  "collected_at": "2026-02-06T02:10:02.196788",
  "compilation_status": "failed",
  "license": "none",
  "license_name": "No License (Assumed)",
  "license_url": null,
  "repo_stars": 0,
  "repo_forks": 0,
  "repo_owner": "jhao",
  "repo_name": "pm-universe",
  "repo_description": "需求分析和产品经理必会的50个行业软件功能",
  "repo_language": "HTML",
  "repo_topics": [],
  "repo_created_at": "2025-10-19T14:19:14Z",
  "repo_updated_at": "2025-11-23T13:14:45Z",
  "compilation_error": "[WinError 2] 系统找不到指定的文件。"
}