{
  "id": "gh_mindmap_01913",
  "source": "github",
  "source_url": "https://github.com/pkcbailey/portal/blob/4d3d01a9f920641c8c3831b4c8d05454d2b75880/azure_dns_mindmap.mmd",
  "github_repo": "pkcbailey/portal",
  "github_file_path": "azure_dns_mindmap.mmd",
  "diagram_type": "mindmap",
  "code": "mindmap\n  root((DNS in Azure))\n    VNETs\n      Address_spaces_subnets\n      Peering_non_transitive_DNS\n      DNS_server_setting\n      Link_to_Private_DNS_zones\n      Registration_vs_Resolution_only\n    Private_DNS_Zones\n      Zone_examples\n        privatelink_blob_core_windows_net\n        privatelink_vaultcore_azure_net\n        privatelink_database_windows_net\n      Virtual_network_links\n        One_zone_to_many_VNETs\n        No_transitive_resolution\n        Auto_registration_optional\n      Records\n        A_AAAA_from_Private_Endpoints\n        PTR_in_VNET_specific_zones\n      Governance\n        RBAC_naming_standards\n        Limits_quotas\n    Private_Endpoints_PE\n      Creates_NIC_with_private_IP\n      Requires_matching_privatelink_zone\n      Auto_create_zone_toggle\n      A_record_resource_guid_to_VNET_IP\n      PE_per_region_per_resource\n    DNS_requirements_on_prem\n      Conditional_forwarders_to_Inbound_endpoints\n    Azure_DNS_Private_Resolver\n      Inbound_endpoints\n        IPs_for_on_prem_other_VNETs\n      Outbound_endpoints\n        Forwarding_rulesets\n        Ruleset_association_to_VNETs\n        Hub_and_spoke_centralization\n        High_availability_2_endpoints\n    Name_Resolution_Paths\n      In_VNET_workload_to_Zone_link\n      On_prem_client_to_FW_Infoblox_DC\n      Spoke_VNET_to_Hub_with_Resolver\n      Public_fallback_only_if_no_private_match\n    Cross_Premises_Hybrid\n      On_prem_to_Conditional_forwarders\n      Azure_to_Outbound_rules\n      Split_horizon_strategy_recursion_controls\n    Cross_Tenant_Multi_Org\n      No_cross_tenant_zone_link\n      Patterns\n        Duplicate_private_zones_per_tenant\n        Shared_hub_in_shared_services_tenant\n        Resolver_to_forward_across_tenants\n        Azure_Lighthouse_for_management_only\n    Governance_Limits\n      Max_links_per_zone_QPS_record_counts\n      Naming_conventions_for_PE_zones\n      DR_BCP_region_pairs_multiple_PEs\n    Troubleshooting\n      nslookup_dig_from_workload_subnet\n      Check_VNET_link_status_auto_registration\n      Validate_Resolver_routing_ruleset_association\n      Confirm_on_prem_conditionals_reach_Inbound_IPs\n      Packet_capture_pcap_Azure_NSG_flow_logs\n",
  "content_size": 2164,
  "collected_at": "2026-02-06T01:54:46.261813",
  "compilation_status": "failed",
  "license": "none",
  "license_name": "No License",
  "license_url": "",
  "repo_stars": 0,
  "repo_forks": 0,
  "repo_owner": "pkcbailey",
  "repo_name": "portal",
  "repo_description": "Dashboards",
  "repo_language": "Python",
  "repo_topics": [],
  "repo_created_at": "2025-10-05T14:49:18Z",
  "repo_updated_at": "2025-11-25T13:52:22Z",
  "compilation_error": "[WinError 2] 系统找不到指定的文件。"
}