{
  "id": "gh_sequence_00691",
  "source": "github",
  "source_url": "https://github.com/mechmind-dwv/mechmind-dwv/blob/9bdf6eb7c4e9f0771e6b79bb90c3a515dbdb836c/docs/robotics/api/rest/sequenceDiagram.mmd",
  "github_repo": "mechmind-dwv/mechmind-dwv",
  "github_file_path": "docs/robotics/api/rest/sequenceDiagram.mmd",
  "diagram_type": "sequence",
  "code": "%% Ejemplo del protocolo\nsequenceDiagram\n    MechBot->>ROS2: /cmd_vel (Twist)\n    ROS2->>ESP32: Serial@115200bps\n    ESP32-->>Sensors: I2C Request\n",
  "content_size": 147,
  "collected_at": "2026-02-06T01:35:45.147256",
  "compilation_status": "failed",
  "license": "none",
  "license_name": "No License (Assumed)",
  "license_url": null,
  "repo_stars": 1,
  "repo_forks": 0,
  "repo_owner": "mechmind-dwv",
  "repo_name": "mechmind-dwv",
  "repo_description": "Config files for my GitHub profile.",
  "repo_language": "Python",
  "repo_topics": [
    "config",
    "github-config"
  ],
  "repo_created_at": "2025-02-19T00:16:18Z",
  "repo_updated_at": "2025-12-10T01:28:12Z",
  "compilation_error": "[WinError 2] 系统找不到指定的文件。"
}