{
  "id": "gh_sequence_00747",
  "source": "github",
  "source_url": "https://github.com/phoax/linea-token-list/blob/c1061274fa8c620407d0a7aedd59e7ae559808ec/tokenizer/docs/mermaid/diagrams/verify-mainnet-shortlist-action.mmd",
  "github_repo": "phoax/linea-token-list",
  "github_file_path": "tokenizer/docs/mermaid/diagrams/verify-mainnet-shortlist-action.mmd",
  "diagram_type": "sequence",
  "code": "sequenceDiagram\n    actor User\n    \n    User->>+GitHub new branch: Create PR\n    GitHub new branch->>GitHub Action: Trigger\n    GitHub Action->>GitHub Action: npm run test\n    GitHub Action->>GitHub Action: Validate JSON\n    GitHub Action->>+verifyMainnetShortlist: Execute\n    verifyMainnetShortlist-->>GitHub Action: graceful stop\n    GitHub Action->>GitHub Action: Check for changes\n    GitHub Action->>GitHub new branch:commit changes\n    GitHub new branch->>-User: Actions successful\n",
  "content_size": 489,
  "collected_at": "2026-02-06T01:36:27.581660",
  "compilation_status": "failed",
  "license": "none",
  "license_name": "No License",
  "license_url": "",
  "repo_stars": 0,
  "repo_forks": 0,
  "compilation_error": "[WinError 2] 系统找不到指定的文件。"
}